isotope/__init__.py
isotope-0.0.1a0.dist-info/DESCRIPTION.rst
isotope-0.0.1a0.dist-info/METADATA
isotope-0.0.1a0.dist-info/RECORD
isotope-0.0.1a0.dist-info/WHEEL
isotope-0.0.1a0.dist-info/metadata.json
isotope-0.0.1a0.dist-info/top_level.txt
