Metadata-Version: 2.0
Name: isotope
Version: 0.0.1a0
Summary: A library to do a stateful logging
Home-page: https://github.com/codekidX/isotope
Author: Ashish Shekar
Author-email: ckrackerx15@gmail.com
License: Apache2
Keywords: logging,logger,stateful-logging
Platform: UNKNOWN
Requires-Python: >=2.6, !=3.0.*, !=3.1.*, !=3.2.*, <4
